tradeforce/__init__.py
tradeforce/backend/__init__.py
tradeforce/backend/backend_core.py
tradeforce/backend/mongodb.py
tradeforce/backend/postgres.py
tradeforce/backend/sql_tables.py
tradeforce/config.py
tradeforce/custom_types.py
tradeforce/exchange/__init__.py
tradeforce/exchange/api.py
tradeforce/exchange/websocket.py
tradeforce/logger.py
tradeforce/main.py
tradeforce/market/__init__.py
tradeforce/market/history.py
tradeforce/market/metrics.py
tradeforce/market/updater.py
tradeforce/simulator/__init__.py
tradeforce/simulator/buys.py
tradeforce/simulator/default_strategies.py
tradeforce/simulator/hyperparam_search.py
tradeforce/simulator/sells.py
tradeforce/simulator/simulator_core.py
tradeforce/simulator/utils.py
tradeforce/trader/__init__.py
tradeforce/trader/buys.py
tradeforce/trader/secure_credentials.py
tradeforce/trader/sells.py
tradeforce/trader/trader_core.py
tradeforce/utils.py
tradeforce-0.0.1.dist-info/METADATA
tradeforce-0.0.1.dist-info/WHEEL
tradeforce-0.0.1.dist-info/RECORD
